<?xml version="1.0" encoding="utf-8"?>
<LanguageData>

  <TR_Deterioration>타이베리움에 노출됨</TR_Deterioration>

  <!-- Infection -->

  <TR_HediffFusing>융합 중</TR_HediffFusing>
  <TR_HediffCrystallizing>결정화되는 중</TR_HediffCrystallizing>
  <TR_HediffCrystallized>결정화</TR_HediffCrystallized>
  <TR_HediffReverse>결정화 제거 중</TR_HediffReverse>
  <TR_HediffHalted>중단됨</TR_HediffHalted>
  <TR_HediffMutation>변이 확률</TR_HediffMutation>
  <TR_Visceral>음성 변이</TR_Visceral>
  <TR_Symbiotic>양성 번이</TR_Symbiotic>

  <!-- Visceral Memory -->
  <TR_VisceralMemoryName>{0}의 변이체</TR_VisceralMemoryName>
  <TR_VisceralMemoryKind>{0}의 변이체</TR_VisceralMemoryKind>
  <TR_VisceralMemoryKindName>{0}, {1}의 변이체</TR_VisceralMemoryKindName>
  <TR_VisceralConversion>{0}이 끔찍한 살덩이로 변이했습니다.</TR_VisceralConversion>

  <!-- Natural Structures -->
  <TR_GasDeposit>남은 매장량</TR_GasDeposit>

</LanguageData>