<?xml version="1.0" encoding="utf-8" ?>
<Defs>

	
	<TiberiumRim.TRMainButtonDef>
		<defName>TiberiumTab</defName>
		<label>Tiberium Rim</label>
		<description>Check out Tiberium research.</description>
		<workerClass>MainButtonWorker_ToggleTab</workerClass>
		<tabWindowClass>TiberiumRim.MainTabWindow_TibResearch</tabWindowClass>
		<order>79</order>
		<validWithoutMap>true</validWithoutMap>
		<minimized>True</minimized>
		<iconPath>UI/Icons/TiberiumButton</iconPath>
		<!--<specialIconPath>UI/Icons/TiberiumButtonNew</specialIconPath>-->
	</TiberiumRim.TRMainButtonDef>
	
	<!--
	<MainButtonDef>
		<defName>TiberiumTab</defName>
		<label>Tiberium Rim</label>
		<description>Check out Tiberium research.</description>
		<tabWindowClass>TiberiumRim.MainTabWindow_TibResearch</tabWindowClass>
		<order>79</order>
		<validWithoutMap>true</validWithoutMap>
		<minimized>True</minimized>
		<iconPath>UI/Icons/TiberiumButton</iconPath>
	</MainButtonDef>
	-->	
</Defs>
